neurots/__init__.py
neurots/basic.py
neurots/utils.py
neurots/validator.py
neurots/astrocyte/__init__.py
neurots/astrocyte/context.py
neurots/astrocyte/grower.py
neurots/astrocyte/point_cloud.py
neurots/astrocyte/section.py
neurots/astrocyte/space_colonization.py
neurots/astrocyte/tmd_utils.py
neurots/astrocyte/tree.py
neurots/extract_input/__init__.py
neurots/extract_input/from_TMD.py
neurots/extract_input/from_diameter.py
neurots/extract_input/from_neurom.py
neurots/extract_input/input_distributions.py
neurots/extract_input/input_parameters.py
neurots/generate/__init__.py
neurots/generate/diametrizer.py
neurots/generate/grower.py
neurots/generate/orientations.py
neurots/generate/section.py
neurots/generate/soma.py
neurots/generate/tree.py
neurots/generate/algorithms/__init__.py
neurots/generate/algorithms/abstractgrower.py
neurots/generate/algorithms/barcode.py
neurots/generate/algorithms/basicgrower.py
neurots/generate/algorithms/common.py
neurots/generate/algorithms/tmdgrower.py
neurots/morphmath/__init__.py
neurots/morphmath/bifurcation.py
neurots/morphmath/point_array.py
neurots/morphmath/rotation.py
neurots/morphmath/sample.py
neurots/morphmath/utils.py
neurots/preprocess/__init__.py
neurots/preprocess/exceptions.py
neurots/preprocess/preprocessors.py
neurots/preprocess/relevance_checkers.py
neurots/preprocess/utils.py
neurots/preprocess/validity_checkers.py
neurots/schemas/distributions.json
neurots/schemas/parameters.json
NeuroTS-3.7.0.dist-info/AUTHORS.md
NeuroTS-3.7.0.dist-info/LICENSE.txt
NeuroTS-3.7.0.dist-info/METADATA
NeuroTS-3.7.0.dist-info/WHEEL
NeuroTS-3.7.0.dist-info/top_level.txt
NeuroTS-3.7.0.dist-info/RECORD
