Metadata-Version: 2.1
Name: NeuroTS
Version: 3.7.0
Summary: Synthesis of artificial neurons using their topological profiles package.
Home-page: https://NeuroTS.readthedocs.io
Author: Blue Brain Project, EPFL
License: Apache License 2.0
Project-URL: Tracker, https://github.com/BlueBrain/NeuroTS/issues
Project-URL: Source, https://github.com/BlueBrain/NeuroTS
Classifier: Development Status :: 4 - Beta
Classifier: Intended Audience :: Science/Research
Classifier: License :: OSI Approved :: Apache Software License
Classifier: Programming Language :: Python
Classifier: Programming Language :: Python :: 3
Classifier: Programming Language :: Python :: 3.9
Classifier: Programming Language :: Python :: 3.10
Classifier: Programming Language :: Python :: 3.11
Classifier: Programming Language :: Python :: 3.12
Classifier: Topic :: Scientific/Engineering :: Bio-Informatics
Requires-Python: >=3.9
License-File: LICENSE.txt
License-File: AUTHORS.md
Requires-Dist: jsonschema>=3.0.1
Requires-Dist: importlib-resources>=5; python_version < "3.9"
Requires-Dist: matplotlib>=3.4
Requires-Dist: morphio<4.0,>=3.3.6
Requires-Dist: neurom<4.0,>=3.0
Requires-Dist: numpy<2,>=1.22.0
Requires-Dist: packaging>=20
Requires-Dist: scipy>=1.6
Requires-Dist: tmd>=2.3.0
Requires-Dist: diameter-synthesis>=0.5.4
Provides-Extra: docs
Requires-Dist: docutils<0.21; extra == "docs"
Requires-Dist: m2r2; extra == "docs"
Requires-Dist: sphinx; extra == "docs"
Requires-Dist: sphinx-bluebrain-theme; extra == "docs"
Requires-Dist: sphinx-gallery; extra == "docs"
Requires-Dist: sphinx-jsonschema; extra == "docs"
Provides-Extra: test
Requires-Dist: dictdiffer>=0.5; extra == "test"
Requires-Dist: mock>=3; extra == "test"
Requires-Dist: morph-tool>=2.9; extra == "test"
Requires-Dist: pytest-cov>=4.1; extra == "test"
Requires-Dist: pytest-html>=3.2; extra == "test"
Requires-Dist: pytest-xdist>=2; extra == "test"
Requires-Dist: pytest>=6.1; extra == "test"
Requires-Dist: tqdm>=4.8.4; extra == "test"
